<annotation>
	<folder>camera</folder>
	<filename>2019-11-28_175004.jpg</filename>
	<path>C:\Users\moaz_\PycharmProjects\cnn_testing\camera\2019-11-28_175004.jpg</path>
	<source>
		<database>Unknown</database>
	</source>
	<size>
		<width>2592</width>
		<height>1944</height>
		<depth>3</depth>
	</size>
	<segmented>0</segmented>
	<object>
		<name>Red traffic light</name>
		<pose>Unspecified</pose>
		<truncated>0</truncated>
		<difficult>0</difficult>
		<bndbox>
			<xmin>677</xmin>
			<ymin>563</ymin>
			<xmax>760</xmax>
			<ymax>718</ymax>
		</bndbox>
	</object>
	<object>
		<name>Stop sign</name>
		<pose>Unspecified</pose>
		<truncated>0</truncated>
		<difficult>0</difficult>
		<bndbox>
			<xmin>865</xmin>
			<ymin>564</ymin>
			<xmax>943</xmax>
			<ymax>645</ymax>
		</bndbox>
	</object>
	<object>
		<name>straight</name>
		<pose>Unspecified</pose>
		<truncated>0</truncated>
		<difficult>0</difficult>
		<bndbox>
			<xmin>317</xmin>
			<ymin>1194</ymin>
			<xmax>615</xmax>
			<ymax>1324</ymax>
		</bndbox>
	</object>
	<object>
		<name>straight</name>
		<pose>Unspecified</pose>
		<truncated>0</truncated>
		<difficult>0</difficult>
		<bndbox>
			<xmin>530</xmin>
			<ymin>1053</ymin>
			<xmax>761</xmax>
			<ymax>1172</ymax>
		</bndbox>
	</object>
	<object>
		<name>straight</name>
		<pose>Unspecified</pose>
		<truncated>0</truncated>
		<difficult>0</difficult>
		<bndbox>
			<xmin>688</xmin>
			<ymin>976</ymin>
			<xmax>846</xmax>
			<ymax>1047</ymax>
		</bndbox>
	</object>
	<object>
		<name>straight</name>
		<pose>Unspecified</pose>
		<truncated>0</truncated>
		<difficult>0</difficult>
		<bndbox>
			<xmin>834</xmin>
			<ymin>774</ymin>
			<xmax>952</xmax>
			<ymax>880</ymax>
		</bndbox>
	</object>
	<object>
		<name>straight</name>
		<pose>Unspecified</pose>
		<truncated>0</truncated>
		<difficult>0</difficult>
		<bndbox>
			<xmin>1552</xmin>
			<ymin>722</ymin>
			<xmax>1682</xmax>
			<ymax>778</ymax>
		</bndbox>
	</object>
	<object>
		<name>straight</name>
		<pose>Unspecified</pose>
		<truncated>0</truncated>
		<difficult>0</difficult>
		<bndbox>
			<xmin>1688</xmin>
			<ymin>799</ymin>
			<xmax>1819</xmax>
			<ymax>844</ymax>
		</bndbox>
	</object>
	<object>
		<name>straight</name>
		<pose>Unspecified</pose>
		<truncated>0</truncated>
		<difficult>0</difficult>
		<bndbox>
			<xmin>1838</xmin>
			<ymin>878</ymin>
			<xmax>1988</xmax>
			<ymax>949</ymax>
		</bndbox>
	</object>
	<object>
		<name>straight</name>
		<pose>Unspecified</pose>
		<truncated>0</truncated>
		<difficult>0</difficult>
		<bndbox>
			<xmin>2007</xmin>
			<ymin>988</ymin>
			<xmax>2211</xmax>
			<ymax>1057</ymax>
		</bndbox>
	</object>
	<object>
		<name>straight</name>
		<pose>Unspecified</pose>
		<truncated>0</truncated>
		<difficult>0</difficult>
		<bndbox>
			<xmin>2205</xmin>
			<ymin>1115</ymin>
			<xmax>2436</xmax>
			<ymax>1184</ymax>
		</bndbox>
	</object>
	<object>
		<name>straight</name>
		<pose>Unspecified</pose>
		<truncated>0</truncated>
		<difficult>0</difficult>
		<bndbox>
			<xmin>2</xmin>
			<ymin>1555</ymin>
			<xmax>207</xmax>
			<ymax>1669</ymax>
		</bndbox>
	</object>
	<object>
		<name>straight</name>
		<pose>Unspecified</pose>
		<truncated>1</truncated>
		<difficult>0</difficult>
		<bndbox>
			<xmin>2427</xmin>
			<ymin>1244</ymin>
			<xmax>2592</xmax>
			<ymax>1267</ymax>
		</bndbox>
	</object>
	<object>
		<name>left</name>
		<pose>Unspecified</pose>
		<truncated>0</truncated>
		<difficult>0</difficult>
		<bndbox>
			<xmin>473</xmin>
			<ymin>715</ymin>
			<xmax>665</xmax>
			<ymax>749</ymax>
		</bndbox>
	</object>
	<object>
		<name>left</name>
		<pose>Unspecified</pose>
		<truncated>0</truncated>
		<difficult>0</difficult>
		<bndbox>
			<xmin>1252</xmin>
			<ymin>672</ymin>
			<xmax>1507</xmax>
			<ymax>709</ymax>
		</bndbox>
	</object>
	<object>
		<name>left</name>
		<pose>Unspecified</pose>
		<truncated>0</truncated>
		<difficult>0</difficult>
		<bndbox>
			<xmin>957</xmin>
			<ymin>703</ymin>
			<xmax>1017</xmax>
			<ymax>759</ymax>
		</bndbox>
	</object>
</annotation>
